poetry_version_plugin/__init__.py
poetry_version_plugin/plugin.py
poetry_version_plugin-0.2.1.dist-info/LICENSE
poetry_version_plugin-0.2.1.dist-info/METADATA
poetry_version_plugin-0.2.1.dist-info/WHEEL
poetry_version_plugin-0.2.1.dist-info/entry_points.txt
poetry_version_plugin-0.2.1.dist-info/RECORD
