Metadata-Version: 2.1
Name: poetry-version-plugin
Version: 0.2.1
Summary: Poetry plugin for dynamically extracting the package version from a __version__ variable or a Git tag.
Home-page: https://github.com/tiangolo/poetry-version-plugin
Author: Sebastián Ramírez
Author-email: tiangolo@gmail.com
Requires-Python: >=3.7,<4.0
Classifier: Development Status :: 3 - Alpha
Classifier: Intended Audience :: Developers
Classifier: Intended Audience :: Information Technology
Classifier: Intended Audience :: System Administrators
Classifier: License :: OSI Approved :: MIT License
Classifier: Operating System :: OS Independent
Classifier: Programming Language :: Python
Classifier: Programming Language :: Python :: 3
Classifier: Programming Language :: Python :: 3.7
Classifier: Programming Language :: Python :: 3.8
Classifier: Programming Language :: Python :: 3.9
Classifier: Programming Language :: Python :: 3.10
Classifier: Programming Language :: Python :: 3.11
Classifier: Programming Language :: Python :: 3 :: Only
Classifier: Topic :: Software Development
Classifier: Topic :: Software Development :: Libraries
Classifier: Topic :: Software Development :: Libraries :: Application Frameworks
Classifier: Topic :: Software Development :: Libraries :: Python Modules
Classifier: Topic :: Software Development :: Version Control :: Git
Classifier: Topic :: System :: Archiving :: Packaging
Classifier: Topic :: System :: Installation/Setup
Classifier: Topic :: System :: Software Distribution
Requires-Dist: poetry (>=1.2.0,<2.0.0)
Project-URL: Documentation, https://github.com/tiangolo/poetry-version-plugin
